Metadata-Version: 2.1
Name: odoo14-addon-stock_available_to_promise_release_exclude_location
Version: 14.0.1.0.1.dev2
Summary: Exclude locations from available stock
Home-page: https://github.com/OCA/wms
Author: ACSONE SA/NV, BCIM, Odoo Community Association (OCA)
Author-email: support@odoo-community.org
License: AGPL-3
Classifier: Programming Language :: Python
Classifier: Framework :: Odoo
Classifier: Framework :: Odoo :: 14.0
Classifier: License :: OSI Approved :: GNU Affero General Public License v3
Requires-Python: >=3.6
Requires-Dist: odoo14-addon-stock-available-immediately-exclude-location
Requires-Dist: odoo14-addon-stock-available-to-promise-release
Requires-Dist: odoo<14.1dev,>=14.0a
